[{"id": 2158, "subject": "極值", "question": "關於「極值」，關於「極值」，下列何者正確？", "options": ["一階導數判定", "與一階導數判定相似但條件不同的情況", "常見但不完全正確的理解", "僅在特定條件下成立的說法"], "answer": 0, "explanation": "【極值】一階導數判定\n💡口訣：【極值】一階導數判定", "difficulty": 3}, {"id": 2159, "subject": "極值", "question": "「極值」的應用，下列何者正確？", "options": ["一階導數判定", "與一階導數判定相似但條件不同的情況", "常見但不完全正確的理解", "僅在特定條件下成立的說法"], "answer": 0, "explanation": "【極值】一階導數判定\n💡口訣：【極值】一階導數判定", "difficulty": 3}, {"id": 2160, "subject": "極值", "question": "關於「極值」，下列何者最能說明「極值」？", "options": ["一階導數判定", "僅在特定條件下成立的說法", "與一階導數判定相似但條件不同的情況", "常見但不完全正確的理解"], "answer": 0, "explanation": "【極值】一階導數判定\n💡口訣：【極值】一階導數判定", "difficulty": 3}]