[{"id": 2002, "subject": "振幅與週期", "question": "下列關於「振幅與週期」的敘述，何者正確？", "options": ["與y=Asin(Bx+相似但條件不同的情況", "常見但不完全正確的理解", "僅在特定條件下成立的說法", "y=Asin(Bx+C)+D"], "answer": 3, "explanation": "【振幅與週期】y=Asin(Bx+C)+D\n💡口訣：【振幅與週期】y=Asin(Bx+C)+D", "difficulty": 3}, {"id": 2003, "subject": "振幅與週期", "question": "「振幅與週期」的應用，下列何者正確？", "options": ["y=Asin(Bx+C)+D", "僅在特定條件下成立的說法", "常見但不完全正確的理解", "與y=Asin(Bx+相似但條件不同的情況"], "answer": 0, "explanation": "【振幅與週期】y=Asin(Bx+C)+D\n💡口訣：【振幅與週期】y=Asin(Bx+C)+D", "difficulty": 3}, {"id": 2004, "subject": "振幅與週期", "question": "下列何者最能說明「振幅與週期」？", "options": ["與y=Asin(Bx+相似但條件不同的情況", "常見但不完全正確的理解", "y=Asin(Bx+C)+D", "僅在特定條件下成立的說法"], "answer": 2, "explanation": "【振幅與週期】y=Asin(Bx+C)+D\n💡口訣：【振幅與週期】y=Asin(Bx+C)+D", "difficulty": 3}]