[{"id": 1974, "subject": "標準差", "question": "關於「標準差」，下列何者正確？", "options": ["標準差意義與計算", "僅在特定條件下成立的說法", "與標準差意義與計算相似但條件不同的情況", "常見但不完全正確的理解"], "answer": 0, "explanation": "【標準差】標準差意義與計算\n💡口訣：【標準差】標準差意義與計算", "difficulty": 2}, {"id": 1975, "subject": "標準差", "question": "根據「標準差」，下列何者正確？", "options": ["與標準差意義與計算相似但條件不同的情況", "僅在特定條件下成立的說法", "常見但不完全正確的理解", "標準差意義與計算"], "answer": 3, "explanation": "【標準差】標準差意義與計算\n💡口訣：【標準差】標準差意義與計算", "difficulty": 2}, {"id": 1976, "subject": "標準差", "question": "關於「標準差」，下列何者最能說明「標準差」？", "options": ["與標準差意義與計算相似但條件不同的情況", "僅在特定條件下成立的說法", "常見但不完全正確的理解", "標準差意義與計算"], "answer": 3, "explanation": "【標準差】標準差意義與計算\n💡口訣：【標準差】標準差意義與計算", "difficulty": 2}]